{
  "id": "does-the-tech-anti-trust-bill-announce-campaign-for-2026",
  "title": "Does The Tech Anti-Trust Bill announce campaign for 2026?",
  "category": "DONOR_INTEL",
  "impliedProbability": 0.29,
  "volume": 3544836,
  "expirationDate": "2026-08-04T02:02:25.898Z",
  "status": "OPEN",
  "fecEdgeAvailable": true,
  "options": [
    {
      "name": "Yes",
      "price": 0.29
    },
    {
      "name": "No",
      "price": 0.71
    }
  ],
  "intel": {
    "summary": "A top donor just pivoted funds to a dark horse candidate.",
    "fecFilings": 3,
    "superPacSpend": 285479
  }
}