{
  "id": "will-gavin-newsom-endorse-a-primary-challenger-in-the-ny-14-primary-9511",
  "title": "Will Gavin Newsom endorse a primary challenger in the NY-14 primary? 9511",
  "category": "DONOR_INTEL",
  "impliedProbability": 0.24,
  "volume": 18766,
  "expirationDate": "2026-07-16T23:38:58.045Z",
  "status": "OPEN",
  "fecEdgeAvailable": true,
  "options": [
    {
      "name": "Yes",
      "price": 0.24
    },
    {
      "name": "No",
      "price": 0.76
    }
  ],
  "intel": {
    "summary": "A top donor just pivoted funds to a dark horse candidate.",
    "fecFilings": 3,
    "superPacSpend": 9115
  }
}